{
  "name": "ratansunpy",
  "version": "0.2.4",
  "summary": "RATAN-600 radioastronomical solar data and methods Python library",
  "author": "['Igor Lysov <iilysov.sci@gmail.com>', 'Irina Knyazeva <iknyazeva@gmail.com>', 'Evgenii Kurochkin <k-u-r-o-k@yandex.ru>', 'Andrey Shendrik <ashend90@gmail.com>', 'Korelov Maksim <mskorelov@gmail.com>']",
  "license": null,
  "home_page": null,
  "download_filename": "ratansunpy-0.2.4-py3-none-any.whl",
  "download_time": "2025-08-21T11:51:53.477972",
  "package_url": "https://pypi.org/project/ratansunpy/"
}